tj010/__init__.py
tj010/mpccore/AsGen.cpython-313-x86_64-linux-gnu.so
tj010/mpccore/DistAdaptive.cpython-313-x86_64-linux-gnu.so
tj010/mpccore/DynamicOptiLayer.cpython-313-x86_64-linux-gnu.so
tj010/mpccore/Filter.cpython-313-x86_64-linux-gnu.so
tj010/mpccore/LPVModel.cpython-313-x86_64-linux-gnu.so
tj010/mpccore/LPVProcessSim.cpython-313-x86_64-linux-gnu.so
tj010/mpccore/MPCController.cpython-313-x86_64-linux-gnu.so
tj010/mpccore/MPCManage.cpython-313-x86_64-linux-gnu.so
tj010/mpccore/NpNmGen.cpython-313-x86_64-linux-gnu.so
tj010/mpccore/Predictor.cpython-313-x86_64-linux-gnu.so
tj010/mpccore/Preprocessing.cpython-313-x86_64-linux-gnu.so
tj010/mpccore/ProcessSim.cpython-313-x86_64-linux-gnu.so
tj010/mpccore/QPsolver5.cpython-313-x86_64-linux-gnu.so
tj010/mpccore/SPCurve.cpython-313-x86_64-linux-gnu.so
tj010/mpccore/StarOptiLayer390.cpython-313-x86_64-linux-gnu.so
tj010/mpccore/__init__.py
tj010/mpccore/utilities.cpython-313-x86_64-linux-gnu.so
tj010/mpcplot/PlotIPYNB.cpython-313-x86_64-linux-gnu.so
tj010/mpcplot/__init__.py
tj010/tj007pyInterface/Controller007.cpython-313-x86_64-linux-gnu.so
tj010/tj007pyInterface/DLL007.py
tj010/tj007pyInterface/DLL007data.py
tj010/tj007pyInterface/__init__.py
tj010/tj007pyInterface/recordData.py
tj010-0.40.1.dist-info/METADATA
tj010-0.40.1.dist-info/WHEEL
tj010-0.40.1.dist-info/top_level.txt
tj010-0.40.1.dist-info/RECORD
