Metadata-Version: 2.4
Name: tj010
Version: 0.40.1
Summary: Tai-Ji MPC algorithm
Author-email: kkzhang <kkzhang3@hotmail.com>
Requires-Python: >=3.12
Requires-Dist: numpy
Requires-Dist: scipy
Requires-Dist: matplotlib
Requires-Dist: taiji_hasp
Requires-Dist: cvxopt
Requires-Dist: scs
Requires-Dist: clarabel
